epflpeople/VERSION
epflpeople/__init__.py
epflpeople/__main__.py
epflpeople/epflpeople.py
epflpeople/errors.py
epflpeople-0.0.7.dist-info/LICENSE
epflpeople-0.0.7.dist-info/METADATA
epflpeople-0.0.7.dist-info/WHEEL
epflpeople-0.0.7.dist-info/entry_points.txt
epflpeople-0.0.7.dist-info/top_level.txt
epflpeople-0.0.7.dist-info/RECORD
