Metadata-Version: 2.1
Name: epflpeople
Version: 0.0.7
Summary: EPFL People API wrapper for python
Home-page: https://github.com/spaenleh/epfl-people-api
Author: spaenleh
Author-email: spaenleh@gmail.com
License: UNKNOWN
Project-URL: Documentation, https://github.com/spaenleh/epfl-people-api/blob/main/README.md
Project-URL: Github, https://github.com/spaenleh/epfl-people-api
Project-URL: Changelog, https://github.com/spaenleh/epfl-people-api/blob/main/CHANGELOG.md
Platform: UNKNOWN
Classifier: License :: OSI Approved :: MIT License
License-File: LICENSE
Requires-Dist: requests
